graveolens.py
graveolens-0.1.4.dist-info/LICENSE
graveolens-0.1.4.dist-info/METADATA
graveolens-0.1.4.dist-info/WHEEL
graveolens-0.1.4.dist-info/top_level.txt
graveolens-0.1.4.dist-info/RECORD
