Metadata-Version: 2.1
Name: graveolens
Version: 0.1.4
Summary: The missing test library for Celery.
Home-page: https://github.com/percipient/graveolens
Author: Percipient Networks, LLC
Author-email: support@strongarm.io
License: Apache 2.0
Download-URL: https://github.com/percipient/graveolens
Platform: UNKNOWN
Classifier: Development Status :: 4 - Beta
Classifier: Programming Language :: Python
Classifier: Programming Language :: Python :: 2
Classifier: Programming Language :: Python :: 2.7
Classifier: Intended Audience :: Developers
Classifier: License :: OSI Approved :: Apache Software License
Classifier: Topic :: Software Development :: Libraries
Classifier: Topic :: System :: Networking
Requires-Dist: celery (>3)
Requires-Dist: mock (>=2.0.0)
